[
  {
    "eid": "2013012001",
    "gsis": "55833",
    "d": "Sun",
    "t": "3:00",
    "q": "F",
    "k": "",
    "h": "ATL",
    "hnn": "falcons",
    "hs": "24",
    "v": "SF",
    "vnn": "49ers",
    "vs": "28",
    "p": "",
    "rz": "",
    "ga": "",
    "gt": "CON"
  },
  {
    "eid": "2013012000",
    "gsis": "55834",
    "d": "Sun",
    "t": "6:30",
    "q": "F",
    "k": "",
    "h": "NE",
    "hnn": "patriots",
    "hs": "13",
    "v": "BAL",
    "vnn": "ravens",
    "vs": "28",
    "p": "",
    "rz": "",
    "ga": "",
    "gt": "CON"
  }
]